mtmtorch/__init__.py
mtmtorch/blocks.py
mtmtorch/checkpoint.py
mtmtorch/itorch.py
mtmtorch/train.py
mtmtorch-1.0.4.dist-info/LICENSE
mtmtorch-1.0.4.dist-info/METADATA
mtmtorch-1.0.4.dist-info/WHEEL
mtmtorch-1.0.4.dist-info/top_level.txt
mtmtorch-1.0.4.dist-info/RECORD
