Metadata-Version: 2.1
Name: mtmtorch
Version: 1.0.4
Summary: imutum's torch utils
License: MIT License
Classifier: Development Status :: 3 - Alpha
Classifier: Programming Language :: Python :: 3.10
Classifier: Intended Audience :: Developers
Classifier: License :: OSI Approved :: MIT License
Classifier: Operating System :: MacOS
Classifier: Operating System :: POSIX :: Linux
Classifier: Operating System :: Microsoft :: Windows
Requires-Python: >=3.10
License-File: LICENSE
Requires-Dist: torch
Requires-Dist: scikit-learn
Requires-Dist: einops
